Workbook

Sheet README
A1: ANSWER KEY - Kill the Quote Spreadsheet demo dataset
A3: Category: corrugated packaging. Buyer: consumer electronics maker, Pune plant. Annual spend about Rs 4 crore at these quantities.
A4: FX assumption: 1 USD = 85.0 INR (demo rate, configurable in the app). GST and freight are not added to any price.
A5: Vendor B prices are shown NET of the 4% footnote discount, and only after the buyer confirms 1 box = 1 piece for the per-100-pcs lines.
A6: Vendor E 'rest same as last year' is shown in the Om Sai assumed column; the app should flag it as an unconfirmed baseline, not a quote.
A7: Quality gate = ISO 9001 Yes AND burst test report Yes. Vendor B fails (report pending). Vendor E is unknown (burst not stated).
A8: Sheets: Normalized (correct INR price per RFx unit), Eligibility, Split award (live formulas), Expected flags, Commercial terms.

Sheet Normalized
A1: ID | B1: Item | C1: UoM | D1: Annual qty | E1: A Shree | F1: B Deccan | G1: C Pune Box | H1: D Maruti | I1: E Om Sai (quoted) | J1: E Om Sai (assumed = last yr, unconfirmed) | K1: Last year rate | L1: Notes
A2: 1 | B2: 3-ply RSC shipper box 12x10x8 in | C2: box | D2: 84000 | E2: 17.5 | F2: 16.32 | G2: 18.5 | H2: 17.5 | J2: 18.5 | K2: 18.5
A3: 2 | B3: 3-ply RSC shipper box 14x12x10 in | C3: box | D3: 70000 | E3: 23.5 | F3: 21.12 | G3: 23.5 | H3: 24 | J3: 25 | K3: 25
A4: 3 | B4: 3-ply RSC shipper box 16x12x10 in | C4: box | D4: 56000 | E4: 29.5 | F4: 25.92 | G4: 29 | H4: 29 | J4: 29.5 | K4: 29.5
A5: 4 | B5: 3-ply RSC shipper box 18x14x12 in | C5: box | D5: 42000 | E5: 36.5 | F5: 32.64 | G5: 38 | H5: 38.5 | J5: 39.5 | K5: 39.5
A6: 5 | B6: 3-ply RSC shipper box 20x16x12 in | C6: box | D6: 28000 | E6: 52 | F6: 44.64 | G6: 52 | H6: 50 | J6: 53 | K6: 53
A7: 6 | B7: 5-ply RSC shipper box 12x10x8 in | C7: box | D7: 70000 | E7: 33.5 | F7: 29.76 | G7: 33.5 | H7: 33 | J7: 34.5 | K7: 34.5 | L7: B quoted per 100 pcs; UNIT_MISMATCH until confirmed; net of 4% discount
A8: 7 | B8: 5-ply RSC shipper box 14x12x10 in | C8: box | D8: 56000 | E8: 42.5 | F8: 39.84 | G8: 44.5 | H8: 42.5 | J8: 45 | K8: 45 | L8: B quoted per 100 pcs; UNIT_MISMATCH until confirmed; net of 4% discount
A9: 8 | B9: 5-ply RSC shipper box 16x12x10 in | C9: box | D9: 49000 | E9: 52 | F9: 46.08 | G9: 53.5 | H9: 52.5 | J9: 53.5 | K9: 53.5 | L9: B quoted per 100 pcs; UNIT_MISMATCH until confirmed; net of 4% discount
A10: 9 | B10: 5-ply RSC shipper box 18x14x12 in | C10: box | D10: 35000 | E10: 65.5 | F10: 60 | G10: 67 | H10: 69 | J10: 70.5 | K10: 70.5 | L10: B quoted per 100 pcs; UNIT_MISMATCH until confirmed; net of 4% discount; D value unclear in photo (LOW_CONFIDENCE)
A11: 10 | B11: 5-ply RSC shipper box 20x16x12 in | C11: box | D11: 21000 | E11: 91.8 | F11: 82.56 | G11: 92.5 | H11: 87.5 | J11: 94 | K11: 94 | L11: A quoted USD 1.08 x 85.0; B quoted per 100 pcs; UNIT_MISMATCH until confirmed; net of 4% discount
A12: 11 | B12: 7-ply RSC shipper box 16x12x10 in | C12: box | D12: 21000 | E12: 75.65 | F12: 69.6 | G12: 74.5 | H12: 74.5 | J12: 79.5 | K12: 79.5 | L12: A quoted USD 0.89 x 85.0
A13: 12 | B13: 7-ply RSC shipper box 18x14x12 in | C13: box | D13: 14000 | E13: 98.6 | F13: 89.76 | G13: 103 | H13: 98 | J13: 105 | K13: 105 | L13: A quoted USD 1.16 x 85.0
A14: 13 | B14: 7-ply RSC shipper box 20x16x12 in | C14: box | D14: 8400 | E14: 136.85 | F14: 125.76 | H14: 132 | J14: 141 | K14: 141 | L14: A quoted USD 1.61 x 85.0; C did not quote (MISSING_ITEM)
A15: 14 | B15: Die-cut mailer Small 8x6x2 in | C15: piece | D15: 56000 | E15: 12.5 | F15: 11.04 | G15: 12.5 | H15: 11.5 | J15: 12.5 | K15: 12.5
A16: 15 | B16: Die-cut mailer Medium 10x8x3 in | C16: piece | D16: 49000 | E16: 15.5 | F16: 13.92 | G16: 16 | H16: 16 | J16: 16.5 | K16: 16.5
A17: 16 | B17: Die-cut mailer Large 12x9x4 in | C17: piece | D17: 35000 | E17: 21.5 | F17: 19.68 | G17: 21.5 | H17: 21 | J17: 23 | K17: 23 | L17: D value unclear in photo (LOW_CONFIDENCE)
A18: 17 | B18: Die-cut mailer XL 14x10x5 in | C18: piece | D18: 21000 | E18: 31.5 | F18: 27.84 | H18: 29 | J18: 32.5 | K18: 32.5 | L18: C did not quote (MISSING_ITEM)
A19: 18 | B19: 4-cell partition 12x10 in | C19: piece | D19: 84000 | E19: 6 | F19: 5.28 | G19: 6 | H19: 6 | J19: 6 | K19: 6
A20: 19 | B20: 6-cell partition 14x12 in | C20: piece | D20: 70000 | E20: 8 | F20: 7.2 | G20: 7.5 | H20: 8 | J20: 8 | K20: 8
A21: 20 | B21: 9-cell partition 16x12 in | C21: piece | D21: 56000 | E21: 11 | F21: 9.6 | G21: 11 | H21: 11 | J21: 11.5 | K21: 11.5
A22: 21 | B22: 3-ply corrugated sheet | C22: kg | D22: 56000 | E22: 39.5 | F22: 35.04 | G22: 36.5 | H22: 38.5 | I22: 38 | K22: 37 | L22: E quoted per kg in email
A23: 22 | B23: 5-ply corrugated sheet | C23: kg | D23: 84000 | E23: 40.5 | F23: 36.48 | G23: 40.5 | H23: 42 | I23: 42 | K23: 41 | L23: E quoted per kg in email
A24: 23 | B24: 7-ply corrugated sheet | C24: kg | D24: 28000 | E24: 48.5 | F24: 41.76 | G24: 45 | H24: 46 | J24: 49.5 | K24: 49.5
A25: 24 | B25: 3-ply corrugated roll 1.6 m | C25: kg | D25: 21000 | E25: 38.5 | F25: 35.52 | G25: 39.5 | H25: 38.5 | J25: 41.5 | K25: 41.5
A26: 25 | B26: 5-ply corrugated roll 1.6 m | C26: kg | D26: 35000 | E26: 42 | F26: 37.44 | G26: 41.5 | H26: 42.5 | J26: 44.5 | K26: 44.5
A27: 26 | B27: Edge protector 35x35x3 mm, 1.0 m | C27: bundle of 25 | D27: 1120 | E27: 301 | F27: 276.48 | G27: 301 | H27: 293 | J27: 322 | K27: 322
A28: 27 | B28: Edge protector 50x50x4 mm, 1.2 m | C28: bundle of 25 | D28: 840 | E28: 414 | F28: 360.96 | G28: 412 | H28: 425 | J28: 430 | K28: 430
A29: 28 | B29: Edge protector 50x50x5 mm, 1.5 m | C29: bundle of 25 | D29: 560 | E29: 574 | F29: 506.88 | H29: 561 | J29: 573 | K29: 573 | L29: C did not quote (MISSING_ITEM)
A30: 29 | B30: Pallet cap 1200x1000 in | C30: piece | D30: 11200 | E30: 45.05 | F30: 41.76 | G30: 44 | H30: 46.5 | J30: 47.5 | K30: 47.5 | L30: A quoted USD 0.53 x 85.0
A31: 30 | B31: Pallet cap 1200x800 in | C31: piece | D31: 8400 | E31: 58.65 | F31: 52.32 | G31: 57 | H31: 58 | J31: 60 | K31: 60 | L31: A quoted USD 0.69 x 85.0

Sheet Eligibility
A1: Vendor | B1: ISO 9001 | C1: Burst report | D1: Passes gate (1/0) | E1: Lead time (days) | F1: FSC | G1: 60-day terms | H1: Note
A2: A Shree | B2: Yes | C2: Yes | D2: =IF(AND(B2="Yes",C2="Yes"),1,0) -> 1 | E2: 14 | F2: Yes | G2: Accepted | H2: Certificate and report attached
A3: B Deccan | B3: Yes | C3: No | D3: =IF(AND(B3="Yes",C3="Yes"),1,0) -> 0 | E3: 10 | F3: Yes | G3: No (45 days) | H3: Burst report promised after order
A4: C Pune Box | B4: Yes | C4: Yes | D4: =IF(AND(B4="Yes",C4="Yes"),1,0) -> 1 | E4: 10 | F4: No | G4: No (45 days) | H4: Report attached to letter
A5: D Maruti | B5: Yes | C5: Yes | D5: =IF(AND(B5="Yes",C5="Yes"),1,0) -> 1 | E5: 12 | F5: On request | G5: No (30 days) | H5: Report enclosed per rate card
A6: E Om Sai | B6: Yes | C6: Not stated | D6: =IF(AND(B6="Yes",C6="Yes"),1,0) -> 0 | F6: Not stated | G6: Not stated | H6: Email only says 'ISO certified'

Sheet Split award
A1: ID | B1: Item | C1: Annual qty | D1: A Shree | E1: B Deccan | F1: C Pune Box | G1: D Maruti | H1: E Om Sai | I1: Best eligible price | J1: Winner (eligible) | K1: Cost at winner | L1: Best price ignoring gate | M1: Winner ignoring gate | N1: Cost ignoring gate | O1: Last year cost
A2: =Normalized!A2 -> 1 | B2: =Normalized!B2 -> 3-ply RSC shipper box 12x10x8 in | C2: =Normalized!D2 -> 84000 | D2: =IF(AND(Eligibility!$D$2=1,ISNUMBER(Normalized!E2)),Normalized!E2,"") -> 17.5 | E2: =IF(AND(Eligibility!$D$3=1,ISNUMBER(Normalized!F2)),Normalized!F2,"") | F2: =IF(AND(Eligibility!$D$4=1,ISNUMBER(Normalized!G2)),Normalized!G2,"") -> 18.5 | G2: =IF(AND(Eligibility!$D$5=1,ISNUMBER(Normalized!H2)),Normalized!H2,"") -> 17.5 | H2: =IF(AND(Eligibility!$D$6=1,ISNUMBER(Normalized!I2)),Normalized!I2,"") | I2: =IF(COUNT(D2:H2)=0,"",MIN(D2:H2)) -> 17.5 | J2: =IF(I2="","",INDEX($D$1:$H$1,MATCH(I2,D2:H2,0))) -> A Shree | K2: =IF(I2="","",C2*I2) -> 1470000 | L2: =MIN(Normalized!E2:I2) -> 16.32 | M2: =INDEX(Normalized!$E$1:$I$1,MATCH(L2,Normalized!E2:I2,0)) -> B Deccan | N2: =C2*L2 -> 1370880 | O2: =C2*Normalized!K2 -> 1554000
A3: =Normalized!A3 -> 2 | B3: =Normalized!B3 -> 3-ply RSC shipper box 14x12x10 in | C3: =Normalized!D3 -> 70000 | D3: =IF(AND(Eligibility!$D$2=1,ISNUMBER(Normalized!E3)),Normalized!E3,"") -> 23.5 | E3: =IF(AND(Eligibility!$D$3=1,ISNUMBER(Normalized!F3)),Normalized!F3,"") | F3: =IF(AND(Eligibility!$D$4=1,ISNUMBER(Normalized!G3)),Normalized!G3,"") -> 23.5 | G3: =IF(AND(Eligibility!$D$5=1,ISNUMBER(Normalized!H3)),Normalized!H3,"") -> 24 | H3: =IF(AND(Eligibility!$D$6=1,ISNUMBER(Normalized!I3)),Normalized!I3,"") | I3: =IF(COUNT(D3:H3)=0,"",MIN(D3:H3)) -> 23.5 | J3: =IF(I3="","",INDEX($D$1:$H$1,MATCH(I3,D3:H3,0))) -> A Shree | K3: =IF(I3="","",C3*I3) -> 1645000 | L3: =MIN(Normalized!E3:I3) -> 21.12 | M3: =INDEX(Normalized!$E$1:$I$1,MATCH(L3,Normalized!E3:I3,0)) -> B Deccan | N3: =C3*L3 -> 1478400 | O3: =C3*Normalized!K3 -> 1750000
A4: =Normalized!A4 -> 3 | B4: =Normalized!B4 -> 3-ply RSC shipper box 16x12x10 in | C4: =Normalized!D4 -> 56000 | D4: =IF(AND(Eligibility!$D$2=1,ISNUMBER(Normalized!E4)),Normalized!E4,"") -> 29.5 | E4: =IF(AND(Eligibility!$D$3=1,ISNUMBER(Normalized!F4)),Normalized!F4,"") | F4: =IF(AND(Eligibility!$D$4=1,ISNUMBER(Normalized!G4)),Normalized!G4,"") -> 29 | G4: =IF(AND(Eligibility!$D$5=1,ISNUMBER(Normalized!H4)),Normalized!H4,"") -> 29 | H4: =IF(AND(Eligibility!$D$6=1,ISNUMBER(Normalized!I4)),Normalized!I4,"") | I4: =IF(COUNT(D4:H4)=0,"",MIN(D4:H4)) -> 29 | J4: =IF(I4="","",INDEX($D$1:$H$1,MATCH(I4,D4:H4,0))) -> C Pune Box | K4: =IF(I4="","",C4*I4) -> 1624000 | L4: =MIN(Normalized!E4:I4) -> 25.92 | M4: =INDEX(Normalized!$E$1:$I$1,MATCH(L4,Normalized!E4:I4,0)) -> B Deccan | N4: =C4*L4 -> 1451520 | O4: =C4*Normalized!K4 -> 1652000
A5: =Normalized!A5 -> 4 | B5: =Normalized!B5 -> 3-ply RSC shipper box 18x14x12 in | C5: =Normalized!D5 -> 42000 | D5: =IF(AND(Eligibility!$D$2=1,ISNUMBER(Normalized!E5)),Normalized!E5,"") -> 36.5 | E5: =IF(AND(Eligibility!$D$3=1,ISNUMBER(Normalized!F5)),Normalized!F5,"") | F5: =IF(AND(Eligibility!$D$4=1,ISNUMBER(Normalized!G5)),Normalized!G5,"") -> 38 | G5: =IF(AND(Eligibility!$D$5=1,ISNUMBER(Normalized!H5)),Normalized!H5,"") -> 38.5 | H5: =IF(AND(Eligibility!$D$6=1,ISNUMBER(Normalized!I5)),Normalized!I5,"") | I5: =IF(COUNT(D5:H5)=0,"",MIN(D5:H5)) -> 36.5 | J5: =IF(I5="","",INDEX($D$1:$H$1,MATCH(I5,D5:H5,0))) -> A Shree | K5: =IF(I5="","",C5*I5) -> 1533000 | L5: =MIN(Normalized!E5:I5) -> 32.64 | M5: =INDEX(Normalized!$E$1:$I$1,MATCH(L5,Normalized!E5:I5,0)) -> B Deccan | N5: =C5*L5 -> 1370880 | O5: =C5*Normalized!K5 -> 1659000
A6: =Normalized!A6 -> 5 | B6: =Normalized!B6 -> 3-ply RSC shipper box 20x16x12 in | C6: =Normalized!D6 -> 28000 | D6: =IF(AND(Eligibility!$D$2=1,ISNUMBER(Normalized!E6)),Normalized!E6,"") -> 52 | E6: =IF(AND(Eligibility!$D$3=1,ISNUMBER(Normalized!F6)),Normalized!F6,"") | F6: =IF(AND(Eligibility!$D$4=1,ISNUMBER(Normalized!G6)),Normalized!G6,"") -> 52 | G6: =IF(AND(Eligibility!$D$5=1,ISNUMBER(Normalized!H6)),Normalized!H6,"") -> 50 | H6: =IF(AND(Eligibility!$D$6=1,ISNUMBER(Normalized!I6)),Normalized!I6,"") | I6: =IF(COUNT(D6:H6)=0,"",MIN(D6:H6)) -> 50 | J6: =IF(I6="","",INDEX($D$1:$H$1,MATCH(I6,D6:H6,0))) -> D Maruti | K6: =IF(I6="","",C6*I6) -> 1400000 | L6: =MIN(Normalized!E6:I6) -> 44.64 | M6: =INDEX(Normalized!$E$1:$I$1,MATCH(L6,Normalized!E6:I6,0)) -> B Deccan | N6: =C6*L6 -> 1249920 | O6: =C6*Normalized!K6 -> 1484000
A7: =Normalized!A7 -> 6 | B7: =Normalized!B7 -> 5-ply RSC shipper box 12x10x8 in | C7: =Normalized!D7 -> 70000 | D7: =IF(AND(Eligibility!$D$2=1,ISNUMBER(Normalized!E7)),Normalized!E7,"") -> 33.5 | E7: =IF(AND(Eligibility!$D$3=1,ISNUMBER(Normalized!F7)),Normalized!F7,"") | F7: =IF(AND(Eligibility!$D$4=1,ISNUMBER(Normalized!G7)),Normalized!G7,"") -> 33.5 | G7: =IF(AND(Eligibility!$D$5=1,ISNUMBER(Normalized!H7)),Normalized!H7,"") -> 33 | H7: =IF(AND(Eligibility!$D$6=1,ISNUMBER(Normalized!I7)),Normalized!I7,"") | I7: =IF(COUNT(D7:H7)=0,"",MIN(D7:H7)) -> 33 | J7: =IF(I7="","",INDEX($D$1:$H$1,MATCH(I7,D7:H7,0))) -> D Maruti | K7: =IF(I7="","",C7*I7) -> 2310000 | L7: =MIN(Normalized!E7:I7) -> 29.76 | M7: =INDEX(Normalized!$E$1:$I$1,MATCH(L7,Normalized!E7:I7,0)) -> B Deccan | N7: =C7*L7 -> 2083200 | O7: =C7*Normalized!K7 -> 2415000
A8: =Normalized!A8 -> 7 | B8: =Normalized!B8 -> 5-ply RSC shipper box 14x12x10 in | C8: =Normalized!D8 -> 56000 | D8: =IF(AND(Eligibility!$D$2=1,ISNUMBER(Normalized!E8)),Normalized!E8,"") -> 42.5 | E8: =IF(AND(Eligibility!$D$3=1,ISNUMBER(Normalized!F8)),Normalized!F8,"") | F8: =IF(AND(Eligibility!$D$4=1,ISNUMBER(Normalized!G8)),Normalized!G8,"") -> 44.5 | G8: =IF(AND(Eligibility!$D$5=1,ISNUMBER(Normalized!H8)),Normalized!H8,"") -> 42.5 | H8: =IF(AND(Eligibility!$D$6=1,ISNUMBER(Normalized!I8)),Normalized!I8,"") | I8: =IF(COUNT(D8:H8)=0,"",MIN(D8:H8)) -> 42.5 | J8: =IF(I8="","",INDEX($D$1:$H$1,MATCH(I8,D8:H8,0))) -> A Shree | K8: =IF(I8="","",C8*I8) -> 2380000 | L8: =MIN(Normalized!E8:I8) -> 39.84 | M8: =INDEX(Normalized!$E$1:$I$1,MATCH(L8,Normalized!E8:I8,0)) -> B Deccan | N8: =C8*L8 -> 2231040 | O8: =C8*Normalized!K8 -> 2520000
A9: =Normalized!A9 -> 8 | B9: =Normalized!B9 -> 5-ply RSC shipper box 16x12x10 in | C9: =Normalized!D9 -> 49000 | D9: =IF(AND(Eligibility!$D$2=1,ISNUMBER(Normalized!E9)),Normalized!E9,"") -> 52 | E9: =IF(AND(Eligibility!$D$3=1,ISNUMBER(Normalized!F9)),Normalized!F9,"") | F9: =IF(AND(Eligibility!$D$4=1,ISNUMBER(Normalized!G9)),Normalized!G9,"") -> 53.5 | G9: =IF(AND(Eligibility!$D$5=1,ISNUMBER(Normalized!H9)),Normalized!H9,"") -> 52.5 | H9: =IF(AND(Eligibility!$D$6=1,ISNUMBER(Normalized!I9)),Normalized!I9,"") | I9: =IF(COUNT(D9:H9)=0,"",MIN(D9:H9)) -> 52 | J9: =IF(I9="","",INDEX($D$1:$H$1,MATCH(I9,D9:H9,0))) -> A Shree | K9: =IF(I9="","",C9*I9) -> 2548000 | L9: =MIN(Normalized!E9:I9) -> 46.08 | M9: =INDEX(Normalized!$E$1:$I$1,MATCH(L9,Normalized!E9:I9,0)) -> B Deccan | N9: =C9*L9 -> 2257920 | O9: =C9*Normalized!K9 -> 2621500
A10: =Normalized!A10 -> 9 | B10: =Normalized!B10 -> 5-ply RSC shipper box 18x14x12 in | C10: =Normalized!D10 -> 35000 | D10: =IF(AND(Eligibility!$D$2=1,ISNUMBER(Normalized!E10)),Normalized!E10,"") -> 65.5 | E10: =IF(AND(Eligibility!$D$3=1,ISNUMBER(Normalized!F10)),Normalized!F10,"") | F10: =IF(AND(Eligibility!$D$4=1,ISNUMBER(Normalized!G10)),Normalized!G10,"") -> 67 | G10: =IF(AND(Eligibility!$D$5=1,ISNUMBER(Normalized!H10)),Normalized!H10,"") -> 69 | H10: =IF(AND(Eligibility!$D$6=1,ISNUMBER(Normalized!I10)),Normalized!I10,"") | I10: =IF(COUNT(D10:H10)=0,"",MIN(D10:H10)) -> 65.5 | J10: =IF(I10="","",INDEX($D$1:$H$1,MATCH(I10,D10:H10,0))) -> A Shree | K10: =IF(I10="","",C10*I10) -> 2292500 | L10: =MIN(Normalized!E10:I10) -> 60 | M10: =INDEX(Normalized!$E$1:$I$1,MATCH(L10,Normalized!E10:I10,0)) -> B Deccan | N10: =C10*L10 -> 2100000 | O10: =C10*Normalized!K10 -> 2467500
A11: =Normalized!A11 -> 10 | B11: =Normalized!B11 -> 5-ply RSC shipper box 20x16x12 in | C11: =Normalized!D11 -> 21000 | D11: =IF(AND(Eligibility!$D$2=1,ISNUMBER(Normalized!E11)),Normalized!E11,"") -> 91.8 | E11: =IF(AND(Eligibility!$D$3=1,ISNUMBER(Normalized!F11)),Normalized!F11,"") | F11: =IF(AND(Eligibility!$D$4=1,ISNUMBER(Normalized!G11)),Normalized!G11,"") -> 92.5 | G11: =IF(AND(Eligibility!$D$5=1,ISNUMBER(Normalized!H11)),Normalized!H11,"") -> 87.5 | H11: =IF(AND(Eligibility!$D$6=1,ISNUMBER(Normalized!I11)),Normalized!I11,"") | I11: =IF(COUNT(D11:H11)=0,"",MIN(D11:H11)) -> 87.5 | J11: =IF(I11="","",INDEX($D$1:$H$1,MATCH(I11,D11:H11,0))) -> D Maruti | K11: =IF(I11="","",C11*I11) -> 1837500 | L11: =MIN(Normalized!E11:I11) -> 82.56 | M11: =INDEX(Normalized!$E$1:$I$1,MATCH(L11,Normalized!E11:I11,0)) -> B Deccan | N11: =C11*L11 -> 1733760 | O11: =C11*Normalized!K11 -> 1974000
A12: =Normalized!A12 -> 11 | B12: =Normalized!B12 -> 7-ply RSC shipper box 16x12x10 in | C12: =Normalized!D12 -> 21000 | D12: =IF(AND(Eligibility!$D$2=1,ISNUMBER(Normalized!E12)),Normalized!E12,"") -> 75.65 | E12: =IF(AND(Eligibility!$D$3=1,ISNUMBER(Normalized!F12)),Normalized!F12,"") | F12: =IF(AND(Eligibility!$D$4=1,ISNUMBER(Normalized!G12)),Normalized!G12,"") -> 74.5 | G12: =IF(AND(Eligibility!$D$5=1,ISNUMBER(Normalized!H12)),Normalized!H12,"") -> 74.5 | H12: =IF(AND(Eligibility!$D$6=1,ISNUMBER(Normalized!I12)),Normalized!I12,"") | I12: =IF(COUNT(D12:H12)=0,"",MIN(D12:H12)) -> 74.5 | J12: =IF(I12="","",INDEX($D$1:$H$1,MATCH(I12,D12:H12,0))) -> C Pune Box | K12: =IF(I12="","",C12*I12) -> 1564500 | L12: =MIN(Normalized!E12:I12) -> 69.6 | M12: =INDEX(Normalized!$E$1:$I$1,MATCH(L12,Normalized!E12:I12,0)) -> B Deccan | N12: =C12*L12 -> 1461600 | O12: =C12*Normalized!K12 -> 1669500
A13: =Normalized!A13 -> 12 | B13: =Normalized!B13 -> 7-ply RSC shipper box 18x14x12 in | C13: =Normalized!D13 -> 14000 | D13: =IF(AND(Eligibility!$D$2=1,ISNUMBER(Normalized!E13)),Normalized!E13,"") -> 98.6 | E13: =IF(AND(Eligibility!$D$3=1,ISNUMBER(Normalized!F13)),Normalized!F13,"") | F13: =IF(AND(Eligibility!$D$4=1,ISNUMBER(Normalized!G13)),Normalized!G13,"") -> 103 | G13: =IF(AND(Eligibility!$D$5=1,ISNUMBER(Normalized!H13)),Normalized!H13,"") -> 98 | H13: =IF(AND(Eligibility!$D$6=1,ISNUMBER(Normalized!I13)),Normalized!I13,"") | I13: =IF(COUNT(D13:H13)=0,"",MIN(D13:H13)) -> 98 | J13: =IF(I13="","",INDEX($D$1:$H$1,MATCH(I13,D13:H13,0))) -> D Maruti | K13: =IF(I13="","",C13*I13) -> 1372000 | L13: =MIN(Normalized!E13:I13) -> 89.76 | M13: =INDEX(Normalized!$E$1:$I$1,MATCH(L13,Normalized!E13:I13,0)) -> B Deccan | N13: =C13*L13 -> 1256640 | O13: =C13*Normalized!K13 -> 1470000
... A31: =Normalized!A31 -> 30 | B31: =Normalized!B31 -> Pallet cap 1200x800 in | C31: =Normalized!D31 -> 8400 | D31: =IF(AND(Eligibility!$D$2=1,ISNUMBER(Normalized!E31)),Normalized!E31,"") -> 58.65 | E31: =IF(AND(Eligibility!$D$3=1,ISNUMBER(Normalized!F31)),Normalized!F31,"") | F31: =IF(AND(Eligibility!$D$4=1,ISNUMBER(Normalized!G31)),Normalized!G31,"") -> 57 | G31: =IF(AND(Eligibility!$D$5=1,ISNUMBER(Normalized!H31)),Normalized!H31,"") -> 58 | H31: =IF(AND(Eligibility!$D$6=1,ISNUMBER(Normalized!I31)),Normalized!I31,"") | I31: =IF(COUNT(D31:H31)=0,"",MIN(D31:H31)) -> 57 | J31: =IF(I31="","",INDEX($D$1:$H$1,MATCH(I31,D31:H31,0))) -> C Pune Box | K31: =IF(I31="","",C31*I31) -> 478800 | L31: =MIN(Normalized!E31:I31) -> 52.32 | M31: =INDEX(Normalized!$E$1:$I$1,MATCH(L31,Normalized!E31:I31,0)) -> B Deccan | N31: =C31*L31 -> 439488 | O31: =C31*Normalized!K31 -> 504000
A33: TOTALS | K33: =SUM(K2:K31) -> 38404800 | N33: =SUM(N2:N31) -> 35217101 | O33: =SUM(O2:O31) -> 40534620
A35: SUMMARY
A36: Split award, eligible vendors only (VP question) | B36: =K33 -> 38404800
A37: Split award, ignoring quality gate | B37: =N33 -> 35217101
A38: Last year spend at same quantities | B38: =O33 -> 40534620
A39: Savings vs last year (INR) | B39: =B38-B36 -> 2129820
A40: Savings vs last year (%) | B40: =IF(B38=0,"",B39/B38) -> 0.052543233
A41: Single award A Shree (30 of 30 lines) | B41: =SUMPRODUCT(Normalized!D2:D31,Normalized!E2:E31) -> 39175430
A42: Single award D Maruti (30 of 30 lines) | B42: =SUMPRODUCT(Normalized!D2:D31,Normalized!H2:H31) -> 39078620
A43: Split saving vs best single eligible award (INR) | B43: =MIN(B41,B42)-B36 -> 673820
A44: Lines C Pune Box actually quoted | B44: =COUNT(Normalized!G2:G31) -> 27
A45: Lines Om Sai actually quoted | B45: =COUNT(Normalized!I2:I31) -> 2

Sheet Expected flags
A1: Vendor | B1: Where | C1: Expected flag | D1: What the buyer should see
A2: A Shree | B2: Items 11, 12, 13, 10, 29, 30 | C2: CURRENCY_CONVERTED | D2: INR value, rate 85.0, rate date, original USD kept visible; own-layout Excel with merged cells and section rows still maps to 30 items
A3: B Deccan | B3: Items 6, 7, 8, 9, 10 | C3: UNIT_MISMATCH | D3: Rate is per 100 pcs vs RFx unit box. Blocked until buyer confirms 1 box = 1 piece; app may suggest it but must not auto-resolve
A4: B Deccan | B4: Page footer | C4: DISCOUNT_FOUND | D4: 4% footnote discount applied only on buyer acceptance; footnote shown as source
A5: B Deccan | B5: Compliance section | C5: QUALITY_GATE_FAIL | D5: Burst report 'after order confirmation' = not provided; excluded from eligible split
A6: B Deccan | B6: Terms | C6: AMBIGUOUS_TERM | D6: Freight 'extra at actuals' with no amount
A7: C Pune Box | B7: Items 13, 17, 28 | C7: MISSING_ITEM x3 | D7: Cells marked 'not quoted'; total labelled 27 of 30 lines
A8: C Pune Box | B8: Paragraph | C8: TERMS_IN_PROSE | D8: Freight inclusive only above 500 kg / 200 boxes per drop (conditional); 45-day payment, validity 21 days extracted from a paragraph
A9: D Maruti | B9: Items 9, 16 | C9: LOW_CONFIDENCE | D9: Amber cells with cropped image region; buyer confirms or edits. True values are in the Normalized sheet
A10: D Maruti | B10: Footer | C10: AMBIGUOUS_TERM | D10: Ex-works, freight extra, no amount
A11: E Om Sai | B11: Email line 1 | C11: PARTIAL_QUOTE | D11: Only the 3-ply and 5-ply per-kg sheet lines filled. Rolls are also per kg: acceptable behaviour is to ask which per-kg lines the rates cover
A12: E Om Sai | B12: 'rest same as last year' | C12: BASELINE_REFERENCE | D12: Resolved from last-year file as an assumption, shown separately and excluded from totals until the buyer confirms
... A14: E Om Sai | B14: 'ISO certified' | C14: QUALITY_GATE_UNKNOWN | D14: Burst report not stated; excluded from eligible split with a reason

Sheet Commercial terms
A1: Vendor | B1: Freight | C1: Payment | D1: Validity | E1: GST | F1: Lead time (days)
A2: A Shree | B2: Included, FOR Pune | C2: 60 days | D2: 30 days | E2: 18% extra | F2: 14
A3: B Deccan | B3: Extra at actuals (no amount) | C3: 45 days | D3: 30 days | E3: 18% extra | F3: 10
A4: C Pune Box | B4: Included above 500 kg / 200 boxes per drop; else extra | C4: 45 days | D4: 21 days | E4: 18% extra | F4: 10
A5: D Maruti | B5: Extra (ex-works, no amount) | C5: 30 days | D5: 30 days | E5: 18% extra | F5: 12
A6: E Om Sai | B6: Extra (no amount) | C6: Not stated | D6: Not stated | E6: Not stated | F6: Not stated
